.coveragerc
CONTRIBUTING.rst
LICENSE
MANIFEST.in
README.rst
setup.cfg
setup.py
tasks.py
tox.ini
django_internationalflavor.egg-info/PKG-INFO
django_internationalflavor.egg-info/SOURCES.txt
django_internationalflavor.egg-info/SOURCES.txt.py
django_internationalflavor.egg-info/dependency_links.txt
django_internationalflavor.egg-info/dependency_links.txt.py
django_internationalflavor.egg-info/not-zip-safe
django_internationalflavor.egg-info/top_level.txt
django_internationalflavor.egg-info/top_level.txt.py
docs/Makefile
docs/changelog.rst
docs/conf.py
docs/countries.rst
docs/iban.rst
docs/index.rst
docs/language.rst
docs/make.bat
docs/names.rst
docs/requirements.txt
docs/timezone.rst
docs/vat_number.rst
docs/_build/doctrees/changelog.doctree
docs/_build/doctrees/countries.doctree
docs/_build/doctrees/environment.pickle
docs/_build/doctrees/iban.doctree
docs/_build/doctrees/index.doctree
docs/_build/doctrees/language.doctree
docs/_build/doctrees/names.doctree
docs/_build/doctrees/timezone.doctree
docs/_build/doctrees/vat_number.doctree
docs/_build/html/.buildinfo
docs/_build/html/changelog.html
docs/_build/html/changelog.html.py
docs/_build/html/countries.html
docs/_build/html/countries.html.py
docs/_build/html/genindex.html
docs/_build/html/genindex.html.py
docs/_build/html/iban.html
docs/_build/html/iban.html.py
docs/_build/html/index.html
docs/_build/html/index.html.py
docs/_build/html/language.html
docs/_build/html/language.html.py
docs/_build/html/names.html
docs/_build/html/names.html.py
docs/_build/html/objects.inv
docs/_build/html/py-modindex.html
docs/_build/html/py-modindex.html.py
docs/_build/html/search.html
docs/_build/html/search.html.py
docs/_build/html/searchindex.js
docs/_build/html/timezone.html
docs/_build/html/timezone.html.py
docs/_build/html/vat_number.html
docs/_build/html/vat_number.html.py
docs/_build/html/_sources/changelog.rst.txt
docs/_build/html/_sources/changelog.rst.txt.py
docs/_build/html/_sources/countries.rst.txt
docs/_build/html/_sources/countries.rst.txt.py
docs/_build/html/_sources/iban.rst.txt
docs/_build/html/_sources/iban.rst.txt.py
docs/_build/html/_sources/index.rst.txt
docs/_build/html/_sources/index.rst.txt.py
docs/_build/html/_sources/language.rst.txt
docs/_build/html/_sources/language.rst.txt.py
docs/_build/html/_sources/names.rst.txt
docs/_build/html/_sources/names.rst.txt.py
docs/_build/html/_sources/timezone.rst.txt
