Metadata-Version: 1.1
Name: django-internationalflavor
Version: 0.4.3
Summary: Complementing django-localflavor with fields that are applicable to multiple countries
Home-page: https://github.com/ralphje/django-internationalflavor
Author: Ralph Broenink
Author-email: ralph@ralphbroenink.net
License: MIT
Download-URL: https://github.com/ralphje/django-internationalflavor/tarball/0.4.3
Platform: UNKNOWN
Classifier: Development Status :: 3 - Alpha
Classifier: Environment :: Web Environment
Classifier: Framework :: Django
Classifier: Intended Audience :: Developers
Classifier: License :: OSI Approved :: MIT License
Classifier: Operating System :: OS Independent
Classifier: Programming Language :: Python
Classifier: Programming Language :: Python :: 3
Classifier: Programming Language :: Python :: 3.5
Classifier: Programming Language :: Python :: 3.6
Classifier: Programming Language :: Python :: 3.7
Classifier: Programming Language :: Python :: 3.8
Classifier: Programming Language :: Python :: 3.9
Classifier: Programming Language :: Python :: 3.10
Classifier: Topic :: Internet :: WWW/HTTP
